README.md
setup.py
sanic_csrf/__init__.py
sanic_csrf.egg-info/PKG-INFO
sanic_csrf.egg-info/SOURCES.txt
sanic_csrf.egg-info/dependency_links.txt
sanic_csrf.egg-info/top_level.txt