Metadata-Version: 2.1
Name: sanic-csrf
Version: 0.1.3
Summary: Protection from CSRF attacks for Sanic framework
Home-page: https://bitbucket.org/vlad1777d/sanic_csrf
Author: vlad1777d (Vladislav Naumov)
Author-email: naumovvladislav@mail.ru
License: UNKNOWN
Platform: UNKNOWN
Classifier: Programming Language :: Python :: 3
Classifier: License :: OSI Approved :: MIT License
Classifier: Operating System :: OS Independent
